wisup_e2m/__init__.py
wisup_e2m/configs/__init__.py
wisup_e2m/configs/base.py
wisup_e2m/configs/converters/__init__.py
wisup_e2m/configs/converters/base.py
wisup_e2m/configs/converters/image_converter_config.py
wisup_e2m/configs/converters/text_converter_config.py
wisup_e2m/configs/parsers/__init__.py
wisup_e2m/configs/parsers/base.py
wisup_e2m/configs/parsers/doc_parser_config.py
wisup_e2m/configs/parsers/docx_parser_config.py
wisup_e2m/configs/parsers/epub_parser_config.py
wisup_e2m/configs/parsers/html_parser_config.py
wisup_e2m/configs/parsers/pdf_parser_config.py
wisup_e2m/configs/parsers/ppt_parser_config.py
wisup_e2m/configs/parsers/pptx_parser_config.py
wisup_e2m/configs/parsers/url_parser_config.py
wisup_e2m/configs/parsers/voice_parser_config.py
wisup_e2m/converters/__init__.py
wisup_e2m/converters/base.py
wisup_e2m/converters/image_converter.py
wisup_e2m/converters/main.py
wisup_e2m/converters/strategies/__init__.py
wisup_e2m/converters/strategies/base.py
wisup_e2m/converters/strategies/litellm_strategy.py
wisup_e2m/converters/strategies/prompts/__init__.py
wisup_e2m/converters/strategies/zhipuai_strategy.py
wisup_e2m/converters/text_converter.py
wisup_e2m/parsers/aud/voice_parser.py
wisup_e2m/parsers/base.py
wisup_e2m/parsers/doc/doc_parser.py
wisup_e2m/parsers/doc/docx_parser.py
wisup_e2m/parsers/doc/epub_parser.py
wisup_e2m/parsers/doc/html_parser.py
wisup_e2m/parsers/doc/pdf_parser.py
wisup_e2m/parsers/doc/ppt_parser.py
wisup_e2m/parsers/doc/pptx_parser.py
wisup_e2m/parsers/doc/url_parser.py
wisup_e2m/parsers/img/img_parser.py
wisup_e2m/parsers/main.py
wisup_e2m/utils/__init__.py
wisup_e2m/utils/doc_util.py
wisup_e2m/utils/docx_util.py
wisup_e2m/utils/epub_util.py
wisup_e2m/utils/factory.py
wisup_e2m/utils/image_util.py
wisup_e2m/utils/libreoffice.py
wisup_e2m/utils/llm_utils.py
wisup_e2m/utils/pdf_util.py
wisup_e2m/utils/ppt_util.py
wisup_e2m/utils/pptx_util.py
wisup_e2m/utils/scripts/marker_convert_single.py
wisup_e2m/utils/scripts/pdf_to_images.py
wisup_e2m-0.1.57.dist-info/LICENSE
wisup_e2m-0.1.57.dist-info/METADATA
wisup_e2m-0.1.57.dist-info/WHEEL
wisup_e2m-0.1.57.dist-info/RECORD
