Metadata-Version: 2.1
Name: wisup_e2m
Version: 0.1.57
Summary: Everything to Markdown.
Home-page: https://github.com/wisupai/e2m
License: MIT
Author: Wisup Team
Author-email: team@wisup.a
Requires-Python: >=3.10,<3.13
Classifier: License :: OSI Approved :: MIT License
Classifier: Programming Language :: Python :: 3
Classifier: Programming Language :: Python :: 3.10
Classifier: Programming Language :: Python :: 3.11
Classifier: Programming Language :: Python :: 3.12
Requires-Dist: diskcache (>=5.6.3,<6.0.0)
Requires-Dist: ebooklib (>=0.18,<0.19)
Requires-Dist: litellm (>=1.42.12,<2.0.0)
Requires-Dist: marker-pdf (>=0.2.16,<0.3.0)
Requires-Dist: matplotlib (==3.9.0)
Requires-Dist: nltk (>=3.9,<4.0)
Requires-Dist: pikepdf (>=9.1.0,<10.0.0)
Requires-Dist: pillow-heif (>=0.18.0,<0.19.0)
Requires-Dist: platformdirs (>=4.2.2,<5.0.0)
Requires-Dist: pydantic (>=2.8.2,<3.0.0)
Requires-Dist: pypandoc (>=1.13,<2.0)
Requires-Dist: python-docx (>=1.1.2,<2.0.0)
Requires-Dist: python-pptx (>=1.0.0,<2.0.0)
Requires-Dist: setuptools-rust (>=1.10.1,<2.0.0)
Requires-Dist: speechrecognition (>=3.10.4,<4.0.0)
Requires-Dist: surya-ocr (>=0.4.15,<0.5.0)
Requires-Dist: tomlkit (==0.12.0)
Requires-Dist: torch (>=2.3.0,<3.0.0)
Requires-Dist: unstructured (>=0.15.0,<0.16.0)
Requires-Dist: unstructured-inference (>=0.7.0,<0.8.0)
Requires-Dist: unstructured-pytesseract (>=0.3.0,<0.4.0)
Requires-Dist: zhipuai (>=2.1.4.20230814,<3.0.0.0)
Project-URL: Repository, https://github.com/wisupai/e2m
